time_irreversibility_estimator/__init__.py
time_irreversibility_estimator/time_irreversibility_estimator.py
time_irreversibility_estimator-0.4.3.dist-info/LICENSE
time_irreversibility_estimator-0.4.3.dist-info/METADATA
time_irreversibility_estimator-0.4.3.dist-info/WHEEL
time_irreversibility_estimator-0.4.3.dist-info/top_level.txt
time_irreversibility_estimator-0.4.3.dist-info/RECORD
