Metadata-Version: 2.2
Name: time_irreversibility_estimator
Version: 0.4.3
Summary: A package to estimate time irreversibility in time series using gradient boosting classification.
Home-page: https://github.com/bongiornoc/Time-Irreversibility-Estimator
Author: Christian Bongiorno
Author-email: christian.bongiorno@centralesupelec.fr
Classifier: Programming Language :: Python :: 3
Classifier: License :: OSI Approved :: MIT License
Classifier: Operating System :: OS Independent
Requires-Python: >=3.10
License-File: LICENSE
Requires-Dist: numpy>=2.0.0
Requires-Dist: scikit-learn>=1.5.0
Requires-Dist: xgboost>=2.1.0
Dynamic: author
Dynamic: author-email
Dynamic: classifier
Dynamic: description
Dynamic: description-content-type
Dynamic: home-page
Dynamic: requires-dist
Dynamic: requires-python
Dynamic: summary
